endurance_screen/__init__.py
endurance_screen/endure.py
endurance_screen/main.py
endurance_screen-1.0.1.dist-info/METADATA
endurance_screen-1.0.1.dist-info/WHEEL
endurance_screen-1.0.1.dist-info/entry_points.txt
endurance_screen-1.0.1.dist-info/top_level.txt
endurance_screen-1.0.1.dist-info/RECORD
