Metadata-Version: 2.4
Name: endurance-screen
Version: 1.0.1
Summary: A heads-up display for endurance planning
Requires-Dist: flask
Requires-Dist: requests
